.DS_Store
embedding_adapter/__init__.py
embedding_adapter/embedding_adapter.py
embedding_adapter/embedding_adaptor.py
embedding_adapter/utils.py
embedding_adapter-0.1.1.dist-info/LICENSE
embedding_adapter-0.1.1.dist-info/METADATA
embedding_adapter-0.1.1.dist-info/WHEEL
embedding_adapter-0.1.1.dist-info/top_level.txt
embedding_adapter-0.1.1.dist-info/RECORD
