Metadata-Version: 2.1
Name: embedding-adapter
Version: 0.1.1
Summary: A lightweight open-source package to fine-tune embedding models.
Author: Gabriel Chua
Author-email: cyzgab@gmail.com
License: MIT
Classifier: Programming Language :: Python :: 3
Classifier: License :: OSI Approved :: MIT License
Classifier: Operating System :: OS Independent
Requires-Python: >=3.6
License-File: LICENSE
Requires-Dist: numpy
Requires-Dist: torch
Requires-Dist: tqdm
Requires-Dist: pydantic
Requires-Dist: openai
